MANIFEST.in
setup.py
smart_chart/smartui/.DS_Store
smart_chart/smartui/__init__.py
smart_chart/smartui/admin.py
smart_chart/smartui/apps.py
smart_chart/smartui/forms.py
smart_chart/smartui/widgets.py
smart_chart/smartui/__pycache__/__init__.cpython-39.pyc
smart_chart/smartui/__pycache__/admin.cpython-39.pyc
smart_chart/smartui/__pycache__/apps.cpython-39.pyc
smart_chart/smartui/static/admin/simpleui-x/automatic/dicts.js
smart_chart/smartui/static/admin/simpleui-x/automatic/segment.js
smart_chart/smartui/static/admin/simpleui-x/css/base.css
smart_chart/smartui/static/admin/simpleui-x/css/base.css.map
smart_chart/smartui/static/admin/simpleui-x/css/base.less
smart_chart/smartui/static/admin/simpleui-x/css/index.css
smart_chart/smartui/static/admin/simpleui-x/css/index.css.map
smart_chart/smartui/static/admin/simpleui-x/css/index.less
smart_chart/smartui/static/admin/simpleui-x/css/login.css
smart_chart/smartui/static/admin/simpleui-x/elementui/alert.js
smart_chart/smartui/static/admin/simpleui-x/elementui/aside.js
smart_chart/smartui/static/admin/simpleui-x/elementui/autocomplete.js
smart_chart/smartui/static/admin/simpleui-x/elementui/avatar.js
smart_chart/smartui/static/admin/simpleui-x/elementui/backtop.js
smart_chart/smartui/static/admin/simpleui-x/elementui/badge.js
smart_chart/smartui/static/admin/simpleui-x/elementui/breadcrumb-item.js
smart_chart/smartui/static/admin/simpleui-x/elementui/breadcrumb.js
smart_chart/smartui/static/admin/simpleui-x/elementui/button-group.js
smart_chart/smartui/static/admin/simpleui-x/elementui/button.js
smart_chart/smartui/static/admin/simpleui-x/elementui/calendar.js
smart_chart/smartui/static/admin/simpleui-x/elementui/card.js
smart_chart/smartui/static/admin/simpleui-x/elementui/carousel-item.js
smart_chart/smartui/static/admin/simpleui-x/elementui/carousel.js
smart_chart/smartui/static/admin/simpleui-x/elementui/cascader-panel.js
smart_chart/smartui/static/admin/simpleui-x/elementui/cascader.js
smartui.egg-info/PKG-INFO
smartui.egg-info/SOURCES.txt
smartui.egg-info/dependency_links.txt
smartui.egg-info/not-zip-safe
smartui.egg-info/requires.txt
smartui.egg-info/top_level.txt